Metadata-Version: 2.1
Name: evopython
Version: 0.0.1
Summary: Feature resolution from whole-genome alignment data.
Home-page: https://github.com/fiszbein-lab/evopython
Author: Steven Mick
Author-email: smick@bu.edu
License: bsd-2-clause
Keywords: comparative genomics,evopython
Classifier: Intended Audience :: Science/Research
Classifier: Topic :: Scientific/Engineering :: Bio-Informatics
Classifier: License :: OSI Approved :: BSD License
Classifier: Programming Language :: Python :: 3.10
Requires-Python: >=3.10.8
License-File: LICENSE
